tf2schema/__init__.py
tf2schema/main.py
tf2schema/schemafy.py
tf2schema/webapi.py
tf2schema-0.1.dist-info/LICENSE.txt
tf2schema-0.1.dist-info/METADATA
tf2schema-0.1.dist-info/WHEEL
tf2schema-0.1.dist-info/top_level.txt
tf2schema-0.1.dist-info/RECORD
