Metadata-Version: 2.1
Name: tf2schema
Version: 0.1
Summary: Python lib for various tf2 schema related tasks
Home-page: https://github.com/Jertusz/python-tf2-schema
Author: Jędrzej Szadejko
Author-email: shadyprywatny@gmail.com
License: MIT
Download-URL: https://github.com/Jertusz/python-tf2-schema/releases
Keywords: steam,trade,tf2,teamfortress2,schema
Platform: UNKNOWN
Classifier: Development Status :: 3 - Alpha
Requires-Dist: requests
Requires-Dist: vdf
